setup.py
liuxiaokang_test/__init__.py
liuxiaokang_test/status_code.py
liuxiaokang_test.egg-info/PKG-INFO
liuxiaokang_test.egg-info/SOURCES.txt
liuxiaokang_test.egg-info/dependency_links.txt
liuxiaokang_test.egg-info/top_level.txt