Metadata-Version: 2.1
Name: liuxiaokang-test
Version: 0.0.1
Summary: this is a test packages
Home-page: UNKNOWN
Author: liuxiaokang
Author-email: 1099301992@qq.com
License: UNKNOWN
Platform: UNKNOWN
